healthchecks_manager/__init__.py
healthchecks_manager/healthchecks_api_wrapper.py
healthchecks_manager/manager.py
tests/__init__.py
tests/test_healthchecks.py
python_circleci_package_boilerplate-0.0.1.dist-info/METADATA
python_circleci_package_boilerplate-0.0.1.dist-info/WHEEL
python_circleci_package_boilerplate-0.0.1.dist-info/top_level.txt
python_circleci_package_boilerplate-0.0.1.dist-info/RECORD
